[
    {
        "sender": "Noyon",
        "text": "জীবনটা একা একা চলা সহজ নয়। প্রায় ৪-৫ বছর আগে মা আমাদের ছেড়ে চলে গেছেন। বাবা গ্রামে থাকেন, বড় ভাইয়ের সংসার আলাদা। আমি শহরে ছোট একটি বিজনেস করি, আলহামদুলিল্লাহ, ভালোই চলছে। তবে, একজন ভালো মানুষের সঙ্গী হতে চাই, যার সঙ্গে সুখ-দুঃখ ভাগাভাগি করতে পারি।\n\nএই পোস্টের উদ্দেশ্য একান্তই একজন জীবনসঙ্গী খোঁজা। তাই সবার কাছে বিনীত অনুরোধ, দয়া করে কেউ যেন মশকরা বা ফাইজলামি না করেন, কাটা গায়ে লবণের ছিটা দেবেন না।\n\nযারা এই পোস্টে সত্যিকারভাবে আগ্রহী, তারা এককভাবে (Personally) সরাসরি হোয়াটসঅ্যাপে নক দিবেন — ইনবক্সে নয়। হোয়াটসঅ্যাপ নাম্বার: 01977577641।",
        "timestamp": "12:53"
    },
    {
        "sender": "Mdfaruk",
        "text": "Vai apnar taka ase ki r apni dakte sundhor ki na seta bujen agy vai tarpor porehajgari vai",
        "timestamp": "Tuesday 00:58"
    },
    {
        "sender": "Sheikh M",
        "text": "সাতক্ষীরা খুলনা যশোর ভেতরে কোন পরহেজগার দ্বীন দার মেয়ে থাকলে আমাকে নক দিয়েন",
        "timestamp": "Monday 22:19"
    },
    {
        "sender": "Monir",
        "text": "Not found",
        "timestamp": "Monday 22:19"
    },
    {
        "sender": "Monir",
        "text": "ওয়ালাইকুম সালাম",
        "timestamp": "Monday 22:18"
    },
    {
        "sender": "সবুজ",
        "text": "আসসালামু আলাইকুম",
        "timestamp": "Monday 22:00"
    },
    {
        "sender": "Abu",
        "text": "আসসালামু আলাইকুম,\n#দ্বীনদার_পাত্রী_চাই\n\nপাত্রের বায়োডাটা:\n\nনাম : সুজন\n\nবৈবাহিক অবস্থা : ডিভোর্স ২ বছরের ছেলে বাবু আছে \n\nস্থায়ী ঠিকানা : পঞ্চগড় সদর\n\nবর্তমান ঠিকানা : গাজীপুর\n\nপেশা: গার্মেন্টস টেক্সটাইলের চাকরি (অফিসার )\n\nজন্মসন  :১৯৯৩\n\nশিক্ষাগত যোগ্যতা : মাস্টার্স\n\nরক্তের গ্রুপ :  A+\n\nউচ্চতা : ৫' ৬\"\n\nপিতা : কৃষক \n\nমাতা: গৃহিণী \n\nভাই-বোন : \n২ভাই, ২বোন \n\nপারিবারিক অবস্থা : মধ্যবিত্ত\n***\nসুন্নতী দাড়ি আছে, আল্লাহর বিধান মানার চেষ্টা করি। ধুমপান বা কোন প্রকার নেশায় জরিত নাই। \n***\nযেমন জীবনসঙ্গী আশা করেন : ফরজ, ওয়াজিব, সুন্নাহ মেনে চলেন। কুরআন তিলাওয়াত জানেন। পর্দা করেন। নিয়মিত নামাজ পড়েন।\n\nবয়স: মানানসই।\n\nগাত্রবর্ণ : ফর্সা অথবা মানানসই। \n\nনূন্যতম উচ্চতা: মানানসই।\n\n4th যোগ্যতা: আলেমা/হাফেজা অথবা জেনারেল পড়ুয়া (নূন্যতম SSC/HSC)।\n\nজেলা: উত্তরবঙ্গের জেলা হলে ভালো হয়, তবে পছন্দ হলে যেকোন জেলা।\n\nবৈবাহিক অবস্থা: বিধবা, ডিভোর্সী, অবিবাহীত।\nবিবাহে শর্ত: কোনো প্রকার যৌতুক দাবি করা হবে না। (এ বিষয়ে নিশ্চিত থাকতে পারেন)।মোহরানা নিয়ে কোনো বাড়াবাড়ি করা যাবে না। বিয়ে হবে একদম সুন্নত তরিকায় আল্লাহর রাসূল (সাঃ) যেভাবে বিয়ে করতে বলেছেন সেভাবে বিয়ে হবে। ইনশাআল্লাহ।",
        "timestamp": "Monday 17:59"
    },
    {
        "sender": "Unknown",
        "text": "Not found",
        "timestamp": "Monday 17:59"
    },
    {
        "sender": "Abdul",
        "text": "আসসালামু আলাইকুম ওরাহমাতুল্লাহি ওয়াবারাকাতুহ। জরুরী পাত্র পাত্রীর সন্ধান দাতা। যদি কারো  পাত্র পাত্রী প্রয়োজন হয়। আমার সাথে যোগাযোগ করবেন।সরকারি চাকুরীজীবি,ডাক্তার/ইঞ্জিনিয়ার,বিসিএস ক্যাডার,ব্যাংক কর্মকর্তা, শিক্ষক/প্রফেসর,ব্যবসায়ী/শিল্পপতি,আইনজীবী/ব্যারিস্টার,ইউরোপ/আমেরিকা/অস্ট্রেলিয়া/কানাডা/ইংল্যান্ড/জার্মান/ফ্রান্স/জাপান স্যাটেল  ইনশাআল্লাহ উত্তম ব্যবস্থা হবে প্রয়োজনে আমার মোবাইলে কন্টাক করতে পারেন।01913377558",
        "timestamp": "Monday 13:46"
    },
    {
        "sender": "Mehedi Islam",
        "text": "সতর্ক থাকো এই পাঁচ ধরনের নারীর সাথে বিবাহ সম্পর্কে!\n ১. আন্মানাহ (অভিযোগকারী নারী)\n---\nআন্নানাহ্:-এটি সেই নারী, যে সবসময় অভিযোগ ও কান্নাকাটি করে। সে কিছুতেই সন্তুষ্ট হয় না, এবং কিছুই তার ভালো লাগে না। সে স্বামীর সাথে কখনো স্বস্তিতে থাকতে পারে না। এ ধরনের নারীর সাথে জীবন সুখকর হয় না! স্বামী ঘরে ঢোকার মুহূর্ত থেকে শুরু করে ঘুমানোর আগ পর্যন্ত।\" এবং বাইরে যাওয়ার মুহূর্ত পর্যন্ত সে অভিযোগ শুনতেই থাকে।\n---------\n ২. হান্নানাহ (অন্য স্বামীর প্রতি আকৃষ্ট হওয়া নারী)\n---\nহান্নানাহ্:- অর্থাৎ সে অন্য স্বামীর প্রতি আকৃষ্ট হয়। সে নিজের গুণাবলির জন্য স্বামীকে দোষারোপ করে।\nসে সব সময় স্বামীকে এই বিষয় মনে করিয়ে দেয়।\nসে বলে, \"আমি কেন তোমার মতো একজনের সাথে বিয়ে করলাম?\" সে বলে, \"আমি এমন নই যে তোমার মতো কারো সাথে থাকব। আমার তো আরও ভালো কারো সাথে থাকা উচিত ছিল।\" সে যখনই স্বামীর দিকে তাকায়, তখনই বলে, \"আমার ভাগ্য খারাপ!\" \"আমার মতো মেয়েকে তো এমন একজনের সাথে বিয়ে হওয়া উচিত ছিল, যে আরও ভালো এবং উচ্চমানের।\"\n--------\n ৩. হাদ্দাকাহ (লোভী দৃষ্টিসম্পন্ন নারী)\n---\nযে\"হাদ্দাকাহ\" হলো সেই নারী, যার চোখ সবকিছুর প্রতি যায় এবং সে সব কিছুই পেতে চায়। যদি সে কোনো বাড়িতে যায়, তখন স্বামীর কাছে মন খারাপ করে ফিরে আসে। সে বলে, \"মাশাআল্লাহ! অমুকের কাছে এটা আছে, ওটা আছে, আরও অনেক কিছু আছে।\" \"কিন্তু আমি কত অসহায়! বাজারে গেলে আমি সবকিছুই কিনতে চাই।\"\n--------\n ৪. বাররাকাহ (নিজেকে নিয়ে ব্যস্ত নারী)\n---\n\"বাররাকাহ\" হলো সেই নারী, যে নিজের সৌন্দর্য ও ব্যক্তিগত বিষয়ে ব্যস্ত থাকে এবং স্বামী ও সংসারকে অবহেলা করে। সে শুধু নিজের ব্যাপারেই আগ্রহী। সে তার সাজসজ্জা, ব্যক্তিগত ব্যাপার এবং নিজের অবস্থার দিকেই বেশি মনোযোগ দেয়, স্বামী বা বাড়ির প্রতি নয়! আমরা একে আজকের ভাষায় \"আত্মকেন্দ্রিকতা\" বলতে পারি।\n--------\n ৫. সাদ্দাকাহ (অতিরিক্ত কথা বলা নারী)\n---\nসাদ্দাকাহ\" হলো সেই নারী, যে খুব বেশি কথা বলে।\nসে অনেক বেশি কথা বলে, কিন্তু খুব কমই চুপ থাকে!\n--------\n শায়েখ ড. সুলাইমান আর রুহাইলি (হাফিঃ)",
        "timestamp": "Monday 06:45"
    },
    {
        "sender": "Unknown",
        "text": "100% রাইট",
        "timestamp": "Sunday 19:20"
    },
    {
        "sender": "Monir",
        "text": "Not found",
        "timestamp": "Sunday 19:20"
    },
    {
        "sender": "Monir",
        "text": "ভাই আমি নিজেই পাত্র আমাকে একজনের মেসেজ করছিল যে ভাই ইনবক্সে আসেন কিন্তু পরবর্তীতে ওনাকে আর পাওয়া যাচ্ছে না আমি নিজেই পাত্র",
        "timestamp": "Sunday 18:32"
    },
    {
        "sender": "Monir",
        "text": "Not found",
        "timestamp": "Sunday 18:32"
    },
    {
        "sender": "মোঃআঃ",
        "text": "কোনও ডিভোর্স আপু আছেন?",
        "timestamp": "Sunday 18:31"
    },
    {
        "sender": "Monir",
        "text": "ওয়ালাইকুম আসসালাম আলহামদুলিল্লাহ আল্লাহ ভালো রাখছে ভাই",
        "timestamp": "Sunday 18:31"
    },
    {
        "sender": "মোঃআঃ",
        "text": "কেমন আছেন সবাই।  ভাইয়া / আপুরা",
        "timestamp": "Sunday 18:30"
    },
    {
        "sender": "মোঃআঃ",
        "text": "আসসালামু আলাইকুম",
        "timestamp": "Sunday 18:30"
    },
    {
        "sender": "Monir",
        "text": "ঔ আসসালামু আলাইকুম ভাইজান ইনবক্স করতে বলেন তো কথা পাচ্ছি না তো আপনার বয়স্করা চল্লিশ এর উর্ধ্বে দ্বীনদার পরাজয়ের একজন মহিলার ব্যাপারে কথা বলছিলেন",
        "timestamp": "Sunday 18:30"
    },
    {
        "sender": "Imran",
        "text": "একজন আলেমা পাত্রী আছেন,  পাত্রী এতিম, বয়স ২৫ বছর। পাত্রী শর্ট ডিভোর্স,  সন্তান নেই।  গাজিপুর জেলায় নিজস্ব বাড়ি পাত্রীদের তবে আর্থিক অবস্থা ভালো নয়।  প্রবাসী পাত্র চাচ্ছেন।  পাত্রীর বায়োডাটা দেখতে হোয়াটসঅ্যাপ ( 01600203146) এছাড়াও আরও কিছু আলেমা ও হাফেজা পাত্রী আছেন।",
        "timestamp": "Sunday 18:22"
    },
    {
        "sender": "Unknown",
        "text": "আসসালামু আলাইকুম ভাইয়া\n\nআমাকে  ইনবক্স  করুন",
        "timestamp": "Sunday 18:22"
    },
    {
        "sender": "Monir",
        "text": "Not found",
        "timestamp": "Sunday 18:22"
    },
    {
        "sender": "Monir",
        "text": "আসসালামু আমি একজন 40 এর মধ্যে বয়স্কা দ্বীনদার পরহেজগার জীবনসঙ্গানি চায় যদি তাকে ইনবক্সে যোগাযোগ করুন ০১৭১৮৬৫৫৩৮৪",
        "timestamp": "Sunday 18:18"
    },
    {
        "sender": "HM Mostafijur Rahman",
        "text": "তারা স্বামির ভাগ দিতে রাজি না",
        "timestamp": "Sunday 17:40"
    },
    {
        "sender": "Abdul",
        "text": "আসসালামু আলাইকুম ওরাহমাতুল্লাহি ওয়াবারাকাতুহ। জরুরী পাত্র পাত্রীর সন্ধান দাতা। যদি কারো  পাত্র পাত্রী প্রয়োজন হয়। আমার সাথে যোগাযোগ করবেন।সরকারি চাকুরীজীবি,ডাক্তার/ইঞ্জিনিয়ার,বিসিএস ক্যাডার,ব্যাংক কর্মকর্তা, শিক্ষক/প্রফেসর,ব্যবসায়ী/শিল্পপতি,আইনজীবী/ব্যারিস্টার,ইউরোপ/আমেরিকা/অস্ট্রেলিয়া/কানাডা/ইংল্যান্ড/জার্মান/ফ্রান্স/জাপান স্যাটেল  ইনশাআল্লাহ উত্তম ব্যবস্থা হবে প্রয়োজনে আমার মোবাইলে কন্টাক করতে পারেন।01913377558",
        "timestamp": "Sunday 17:30"
    },
    {
        "sender": "Sheikh M",
        "text": "সাতক্ষীরা খুলনা যশোর ভেতরে কোন পরহেজগার দ্বীন দার মেয়ে থাকলে আমাকে নক দিয়েন",
        "timestamp": "Sunday 17:30"
    },
    {
        "sender": "Monir",
        "text": "Not found",
        "timestamp": "Sunday 17:18"
    },
    {
        "sender": "Sheikh M",
        "text": "সাতক্ষীরা খুলনা যশোর ভেতরে কোন পরহেজগার দ্বীন দার মেয়ে থাকলে আমাকে নক দিয়েন",
        "timestamp": "Sunday 17:18"
    },
    {
        "sender": "محفوظ",
        "text": "দেশে পাত্রীর কোনো অভাব নাই \nপাত্রের অভাব আছে। তবে অনলাইনে আসলে দেখি শুদু পাত্রী চাই পাত্রী চাই",
        "timestamp": "Sunday 16:39"
    },
    {
        "sender": "محفوظ",
        "text": "السلام عليكم و رحمة الله و بركاته",
        "timestamp": "Sunday 16:37"
    },
    {
        "sender": "Unknown",
        "text": "Pete paren jemon amio khujchi patro",
        "timestamp": "Sunday 16:36"
    },
    {
        "sender": "Imran",
        "text": "কিছু আলেমা পাত্রী আছেন মাসনায় আগ্রহী।  পাত্রীদের বায়োডাটা দেখতে WhatsApp( 01600203146) এ নক দিন",
        "timestamp": "Sunday 09:45"
    },
    {
        "sender": "Unknown",
        "text": "আদও কী পাওয়া যাবে আশা করা যায়?",
        "timestamp": "Saturday 19:10"
    },
    {
        "sender": "Unknown",
        "text": "Hi",
        "timestamp": "Saturday 17:56"
    },
    {
        "sender": "রেজোয়ানা",
        "text": "Na",
        "timestamp": "Saturday 17:55"
    },
    {
        "sender": "Unknown",
        "text": "N",
        "timestamp": "Saturday 17:55"
    },
    {
        "sender": "H MD Abdul Majed",
        "text": "Not found",
        "timestamp": "Saturday 17:55"
    },
    {
        "sender": "Tufayel",
        "text": "এখান থেকে কি কেউ পাত্র পাত্রী পেয়েছেন?",
        "timestamp": "Saturday 07:39"
    },
    {
        "sender": "চাঁদপুর",
        "text": "সিরিয়াস পোস্ট পাত্রী পাত্রী পাত্র আমি নিযেই নাম রাজু বয়স ২৫ জেলা চাঁদপুর যেমন পাত্রী চাই পাত্রী যেমনি হোক কোনো সমস্যা নেই তবে সাংসারিক হতে হবে বয়স কোনো বিষয় না যোগাযোগ ইনবক্সে নয়তো 01842731620 হোয়াটসঅ্যাপ ইমু নাম্বার যারা বিয়ের জন্য সিরিয়াস শুধু তারাই নক দিবেন অযথাই কেউ বিরক্ত করবেন না ধন্যবাদ",
        "timestamp": "Friday 07:10"
    },
    {
        "sender": "আমি",
        "text": "দ্রুত বিয়ে করতে ইচ্ছুক এমন ৩০+ পাত্রি প্রয়োজন",
        "timestamp": "Thursday 18:26"
    },
    {
        "sender": "আমি",
        "text": "Not found",
        "timestamp": "Thursday 18:26"
    },
    {
        "sender": "Monir",
        "text": "Not found",
        "timestamp": "Thursday 18:26"
    },
    {
        "sender": "Monir",
        "text": "আসসালামু আলাইকুম ওয়া রাহমাতুল্লাহ",
        "timestamp": "Thursday 18:17"
    },
    {
        "sender": "HM Mostafijur Rahman",
        "text": "Not found",
        "timestamp": "Thursday 18:17"
    },
    {
        "sender": "Md Obaidul",
        "text": "Not found",
        "timestamp": "Thursday 18:17"
    },
    {
        "sender": "Monir",
        "text": "Not found",
        "timestamp": "Thursday 18:17"
    },
    {
        "sender": "Monir",
        "text": "৪০ এর ঊর্ধ্বে বয়স জীবনসঙ্গিনী চাই যদি থাকে দয়া করে কথা বলুন",
        "timestamp": "Thursday 16:45"
    },
    {
        "sender": "রূপকথা",
        "text": "বয়স৪০। শর্ট ডিভোর্সি তাই পাত্রী এর বেবি নাই। বাড়ি গাইবান্ধা লেখাপড়া এইচ  এস সি।৫.২ ইঞ্চি। ফ্যামিলির সবাই শিক্ষিত। দয়া করে ভালো ফ্যামিলির জন্য  নক দিবেন। কেউ মজা করার জন্য নক দিবেন না অনুরোধ। বউ মারা যাওয়া অথবা ডিভোর্সি। ৪০ থেকে ৪৫ বছর বয়সী কেউ। সবাই ঢাকার মধ্যে থাকে কেউ কেউ ঢাকার স্থানীয় দয়া করে ঢাকার মধ্যে যারা আছেন তারা নক দিবেন।যারা সুন্দরী খুঁজেন তারা নক দিবেন না।ভালো মনের সংসারী ধর্ম ভীরু কাউকে জীবন সাথী হিসাবে চাইলে নক pls।",
        "timestamp": "Thursday 16:43"
    },
    {
        "sender": "Md",
        "text": "নাম: মোঃরবিন খাঁন\nবয়স:৩০\nশিক্ষাগত যোগ্যতা:ইন্টার কমপ্লিট,\n বৈবাহিক অবস্থা :সিঙ্গেল,  \nউচ্চতা : ৫ ফুট ৬ইন্চি\nগায়ের বরং :শ্যামলা,\nহোম ডিষ্টিক:নোয়াখালী, \nবর্তমান অবস্হান: ঢাকা\nপেশাঃ সৌদি প্রবাসি,\nপাত্রী:ডিভোর্সি ও বিধবা মেয়েদের অগ্র অধিকার রয়েছে যদি ভালো মনের মানুষ হয়, ধন্যবাদ\n................",
        "timestamp": "Thursday 02:25"
    },
    {
        "sender": "HM Mostafijur Rahman",
        "text": "Not found",
        "timestamp": "Thursday 02:25"
    },
    {
        "sender": "Rifat",
        "text": "গাজীপুর সদরে কেউ আছেন",
        "timestamp": "7 May 2025, 12:52"
    },
    {
        "sender": "Md.",
        "text": "পাত্রের জন্য বিয়ে চাই, লোকেশন চট্টগ্রাম, প্রবাসি",
        "timestamp": "7 May 2025, 01:25"
    },
    {
        "sender": "Adnan",
        "text": "Inbox",
        "timestamp": "6 May 2025, 22:59"
    },
    {
        "sender": "Adnan",
        "text": "Prem korba kew",
        "timestamp": "6 May 2025, 22:59"
    },
    {
        "sender": "Adnan",
        "text": "Cayna mal aktu dekhe niben ",
        "timestamp": "6 May 2025, 22:49"
    },
    {
        "sender": "আমি",
        "text": "Not found",
        "timestamp": "6 May 2025, 22:49"
    },
    {
        "sender": "Monir",
        "text": "Not found",
        "timestamp": "6 May 2025, 22:49"
    },
    {
        "sender": "Unknown",
        "text": "ভালো খবর",
        "timestamp": "5 May 2025, 22:18"
    },
    {
        "sender": "Unknown",
        "text": "আসসালামু আলাইকুম",
        "timestamp": "5 May 2025, 22:17"
    },
    {
        "sender": "Unknown",
        "text": "তাই নাকি",
        "timestamp": "5 May 2025, 22:16"
    },
    {
        "sender": "Md",
        "text": "Not found",
        "timestamp": "5 May 2025, 22:16"
    },
    {
        "sender": "Unknown",
        "text": "আসসালামু আলাইকুম",
        "timestamp": "5 May 2025, 22:12"
    },
    {
        "sender": "HM Mostafijur Rahman",
        "text": "Not found",
        "timestamp": "5 May 2025, 22:12"
    },
    {
        "sender": "Monir",
        "text": "Not found",
        "timestamp": "5 May 2025, 22:12"
    },
    {
        "sender": "Unknown",
        "text": "হায়রে কি দুনিয়া আসলো মেয়ের জন্য পাত্র খুঁজে মা তাও আবার অনলাইনে ",
        "timestamp": "5 May 2025, 22:04"
    },
    {
        "sender": "Md Alamin",
        "text": "Not found",
        "timestamp": "5 May 2025, 22:04"
    },
    {
        "sender": "HM Mostafijur Rahman",
        "text": "Not found",
        "timestamp": "5 May 2025, 22:04"
    },
    {
        "sender": "محفوظ",
        "text": "Not found",
        "timestamp": "5 May 2025, 22:04"
    },
    {
        "sender": "محفوظ",
        "text": "السلام عليكم و رحمة الله و بركاته",
        "timestamp": "5 May 2025, 17:17"
    },
    {
        "sender": "Rahim",
        "text": "Dhakai",
        "timestamp": "5 May 2025, 17:03"
    },
    {
        "sender": "রেজোয়ানা",
        "text": "Cheler bari koi",
        "timestamp": "5 May 2025, 17:02"
    },
    {
        "sender": "Unknown",
        "text": "Kon jaiga",
        "timestamp": "5 May 2025, 16:58"
    },
    {
        "sender": "Unknown",
        "text": "আমাকে একটা নক দিন",
        "timestamp": "5 May 2025, 16:58"
    },
    {
        "sender": "Unknown",
        "text": "ঢাকা কোথায়",
        "timestamp": "5 May 2025, 16:57"
    },
    {
        "sender": "محفوظ",
        "text": "থাকলে যোগাযোগ করবেন",
        "timestamp": "5 May 2025, 16:57"
    },
    {
        "sender": "রেজোয়ানা",
        "text": "Dhaka",
        "timestamp": "5 May 2025, 16:57"
    },
    {
        "sender": "محفوظ",
        "text": "একজন দ্বিনদার পাত্রী চাই",
        "timestamp": "5 May 2025, 16:57"
    },
    {
        "sender": "Unknown",
        "text": "السلام عليكم و رحمة الله و بركاته",
        "timestamp": ""
    }
]